curl2py/__init__.py
curl2py/curl_parser.py
curl2py/utils.py
curl2py-0.0.4.dist-info/entry_points.txt
curl2py-0.0.4.dist-info/LICENSE
curl2py-0.0.4.dist-info/WHEEL
curl2py-0.0.4.dist-info/METADATA
curl2py-0.0.4.dist-info/RECORD
